qat/__init__.py
qat/purr/__init__.py
qat/purr/compiler/__init__.py
qat/purr/compiler/config.py
qat/purr/utils/__init__.py
qat/purr/utils/serializer.py
qat_compiler_minimal-1.1.1.dist-info/METADATA
qat_compiler_minimal-1.1.1.dist-info/WHEEL
qat_compiler_minimal-1.1.1.dist-info/RECORD
