Metadata-Version: 2.1
Name: qat-compiler-minimal
Version: 1.1.1
Summary: A minimal version of the `qat-compiler` package.
License: BSD-3-Clause
Author: Hamid El Maazouz
Author-email: helmaazouz@oxfordquantumcircuits.com
Requires-Python: >=3.8.1,<3.11
Classifier: License :: OSI Approved :: BSD License
Classifier: Programming Language :: Python :: 3
Classifier: Programming Language :: Python :: 3.9
Classifier: Programming Language :: Python :: 3.10
Project-URL: Documentation, https://oqc-community.github.io/qat
